asysocks/__init__.py
asysocks/_version.py
asysocks/certmanager.py
asysocks/client.py
asysocks/security.py
asysocks/server.py
asysocks/authentication/__init__.py
asysocks/common/__init__.py
asysocks/common/aiowrappers.py
asysocks/common/clienturl.py
asysocks/common/comms.py
asysocks/common/constants.py
asysocks/common/credentials.py
asysocks/common/target.py
asysocks/common/trafficlog.py
asysocks/examples/__init__.py
asysocks/examples/socksbrute.py
asysocks/examples/socksportscan.py
asysocks/examples/socksproxy.py
asysocks/examples/sockssec.py
asysocks/examples/sockstunnel.py
asysocks/intercepting/__init__.py
asysocks/intercepting/default_intercept_table.py
asysocks/intercepting/server.py
asysocks/intercepting/target.py
asysocks/intercepting/monitors/__init__.py
asysocks/intercepting/monitors/base.py
asysocks/intercepting/monitors/rawlogging.py
asysocks/intercepting/monitors/sslbase.py
asysocks/network/__init__.py
asysocks/network/queue.py
asysocks/network/tcp.py
asysocks/network/wsnet.py
asysocks/network/wsnetdirect.py
asysocks/network/wsnetws.py
asysocks/protocol/__init__.py
asysocks/protocol/http.py
asysocks/protocol/socks4.py
asysocks/protocol/socks4a.py
asysocks/protocol/socks5.py
asysocks/test/__init__.py
asysocks/test/listener_test.py
asysocks/test/queue_test.py
asysocks/test/ssl_test.py
asysocks/test/test_url_param.py
asysocks/test/wsnettest.py
asysocks/unicomm/__init__.py
asysocks/unicomm/client.py
asysocks/unicomm/server.py
asysocks/unicomm/common/__init__.py
asysocks/unicomm/common/connection.py
asysocks/unicomm/common/proxy.py
asysocks/unicomm/common/target.py
asysocks/unicomm/common/transport.py
asysocks/unicomm/common/unissl.py
asysocks/unicomm/common/packetizers/__init__.py
asysocks/unicomm/common/packetizers/ssl.py
asysocks/unicomm/common/scanner/__init__.py
asysocks/unicomm/common/scanner/common.py
asysocks/unicomm/common/scanner/scanner.py
asysocks/unicomm/common/scanner/targetgen.py
asysocks/unicomm/protocol/__init__.py
asysocks-0.2.17.dist-info/LICENSE
asysocks-0.2.17.dist-info/METADATA
asysocks-0.2.17.dist-info/WHEEL
asysocks-0.2.17.dist-info/entry_points.txt
asysocks-0.2.17.dist-info/top_level.txt
asysocks-0.2.17.dist-info/zip-safe
asysocks-0.2.17.dist-info/RECORD
