Metadata-Version: 2.1
Name: asysocks
Version: 0.2.17
Home-page: https://github.com/skelsec/asysocks
Author: Tamas Jos
Author-email: info@skelsecprojects.com
Classifier: Programming Language :: Python :: 3.6
Classifier: License :: OSI Approved :: MIT License
Classifier: Operating System :: OS Independent
Requires-Python: >=3.6
License-File: LICENSE
Requires-Dist: asn1crypto
Requires-Dist: cryptography
Requires-Dist: h11>=0.14.0
